{
  "tickets": [
    {
      "id": 1,
      "name": "John Doe",
      "class": "Economy",
      "number": 4,
      "from": "New York",
      "date": "2024-08-30",
      "to": "Los Angeles",
      "cost": 299.99
    }
  ],
  "flights": [
    {
      "image": "https://images.unsplash.com/photo-1619679304704-05cd90fb0abd?q=80&w=2070&auto=format&fit=crop&ixlib=rb-4.0.3&ixid=M3wxMjA3fDB8MHxwaG90by1wYWdlfHx8fGVufDB8fHx8fA%3D%3D",
      "id": "FL12345",
      "from": "New York (JFK)",
      "to": "Los Angeles (LAX)",
      "date": "2024-08-30",
      "cost": 350.0
    },
    {
      "image": "https://media.istockphoto.com/id/1987830944/photo/chicago-illinois-usa-downtown-skyline-from-above.jpg?s=1024x1024&w=is&k=20&c=bouM8sR9JPbJ-mE7Krt0UNeE0TjasBbJKTSZFsEDQHY=",
      "id": "FL67890",
      "from": "San Francisco (SFO)",
      "to": "Chicago (ORD)",
      "date": "2024-09-01",
      "cost": 280.0
    },
    {
      "image": "https://images.unsplash.com/photo-1506501139174-099022df5260?q=80&w=2071&auto=format&fit=crop&ixlib=rb-4.0.3&ixid=M3wxMjA3fDB8MHxwaG90by1wYWdlfHx8fGVufDB8fHx8fA%3D%3D",
      "id": "FL23456",
      "from": "Miami (MIA)",
      "to": "Seattle (SEA)",
      "date": "2024-09-05",
      "cost": 400.0
    },
    {
      "image": "https://media.istockphoto.com/id/1182329821/photo/grand-place-square-brussels-belgium.jpg?s=1024x1024&w=is&k=20&c=O9eSyOBWzJPR0Om48frU39JWcGz_Bq3uRInrBY_xpsA=",
      "id": "FL78901",
      "from": "Dallas (DFW)",
      "to": "Denver (DEN)",
      "date": "2024-09-10",
      "cost": 150.0
    },
    {
      "image": "https://plus.unsplash.com/premium_photo-1694475423949-9685bb4fa0bc?w=500&auto=format&fit=crop&q=60&ixlib=rb-4.0.3&ixid=M3wxMjA3fDB8MHxzZWFyY2h8OXx8Ym9zdG9ufGVufDB8fDB8fHww",

      "id": "FL34567",
      "from": "Boston (BOS)",
      "to": "Atlanta (ATL)",
      "date": "2024-09-12",
      "cost": 220.0
    },
    {
      "image": "https://images.unsplash.com/photo-1587223043646-fa771d9e0c8b?w=500&auto=format&fit=crop&q=60&ixlib=rb-4.0.3&ixid=M3wxMjA3fDB8MHxzZWFyY2h8Mnx8bGFzJTIwdmVnYXN8ZW58MHx8MHx8fDA%3D",

      "id": "FL89012",
      "from": "Orlando (MCO)",
      "to": "Las Vegas (LAS)",
      "date": "2024-09-15",
      "cost": 300.0
    },
    {
      "image": "https://media.istockphoto.com/id/1906279786/photo/oceanside-beach-view-aerial.jpg?s=2048x2048&w=is&k=20&c=nGCA_C5dn4Lm646BY6lhrVrMNiKzjQpvUa5sHV_Ltwo=",

      "id": "FL45678",
      "from": "Washington, D.C. (IAD)",
      "to": "San Diego (SAN)",
      "date": "2024-09-20",
      "cost": 370.0
    },
    {
      "image": "https://images.unsplash.com/photo-1502175353174-a7a70e73b362?w=500&auto=format&fit=crop&q=60&ixlib=rb-4.0.3&ixid=M3wxMjA3fDB8MHxzZWFyY2h8Mnx8c2VhdHRsZXxlbnwwfHwwfHx8MA%3D%3D",

      "id": "FL90123",
      "from": "Phoenix (PHX)",
      "to": "Miami (MIA)",
      "date": "2024-09-25",
      "cost": 260.0
    },
    {
      "image": "https://images.unsplash.com/photo-1506383196262-8a562ec7e971?w=500&auto=format&fit=crop&q=60&ixlib=rb-4.0.3&ixid=M3wxMjA3fDB8MHxzZWFyY2h8Mnx8YnJvb2tseW58ZW58MHx8MHx8fDA%3D",

      "id": "FL56789",
      "from": "Houston (IAH)",
      "to": "New York (LGA)",
      "date": "2024-09-28",
      "cost": 210.0
    },
    {
      "image": "https://images.unsplash.com/photo-1705713875094-67f354eaf664?w=500&auto=format&fit=crop&q=60&ixlib=rb-4.0.3&ixid=M3wxMjA3fDB8MHxzZWFyY2h8M3x8aG9ib2tlbnxlbnwwfHwwfHx8MA%3D%3D",

      "id": "FL11223",
      "from": "Seattle (SEA)",
      "to": "Chicago (ORD)",
      "date": "2024-10-01",
      "cost": 330.0
    },
    {
      "image": "https://images.unsplash.com/photo-1473042904451-00171c69419d?w=500&auto=format&fit=crop&q=60&ixlib=rb-4.0.3&ixid=M3wxMjA3fDB8MHxzZWFyY2h8M3x8YXRsYW50YXxlbnwwfHwwfHx8MA%3D%3D",

      "id": "FL33445",
      "from": "Atlanta (ATL)",
      "to": "Los Angeles (LAX)",
      "date": "2024-10-05",
      "cost": 390.0
    }
  ]
}
